{
    "format_version": "1.10.0",
    "minecraft:client_entity": {
        "description": {
            "identifier": "bookshelf_storage:bookshelf_storage_entity",
            "materials": { "default": "entity" },
            "textures": {
                "inventory_0": "textures/entity/bookshelf_storage_0",
                "inventory_20": "textures/entity/bookshelf_storage_20",
                "inventory_100": "textures/entity/bookshelf_storage_100"
            },
            "geometry": {
                "default": "geometry.bookshelf_storage"
            },
            "render_controllers": [ "controller.render.bookshelf_storage" ]
        }
    }
}
